sloppy_xml.py
sloppy_xml-0.3.0.dist-info/licenses/LICENSE
sloppy_xml-0.3.0.dist-info/METADATA
sloppy_xml-0.3.0.dist-info/WHEEL
sloppy_xml-0.3.0.dist-info/top_level.txt
sloppy_xml-0.3.0.dist-info/RECORD
